led_indicator_messager_package/__init__.py
led_indicator_messager_package/led_messager.py
led_indicator_messager-0.0.4.dist-info/LICENSE
led_indicator_messager-0.0.4.dist-info/METADATA
led_indicator_messager-0.0.4.dist-info/WHEEL
led_indicator_messager-0.0.4.dist-info/top_level.txt
led_indicator_messager-0.0.4.dist-info/RECORD
